{
    "_type": "https://in-toto.io/Statement/v0.1",
    "subject": [
        {
            "name": "/nix/store/34vpnpik7b1fb91gwv8pfw7s7v8yir01-gettext-0.21.tar.gz.drv",
            "digest": {
                "sha256": "adab2719e9f2fb61046b9e42fa08d9c1c912ab1368dcde74a60259a9ee8dcd5c"
            }
        }
    ],
    "predicateType": "https://slsa.dev/provenance/v0.2",
    "predicate": {
        "builder": {
            "id": "file://http://nixos.org/drv/0.1"
        },
        "buildType": "https://nixos.org/build/0.1",
        "invocation": {
            "parameters": {
                "args": []
            },
            "environment": {}
        },
        "materials": [
            {
                "uri": "file:///nix/store/s1bb06rzbxlvq08sg0ymwdgcgd1a7xh3-gettext-0.21.tar.gz",
                "digest": {
                    "sha256": "18def2c9ea2c2e5cc1a730709ca2f18a8a105d23c3aa788b07c81e6941ec6477"
                }
            }
        ]
    }
}
